brainrex/__init__.py
brainrex/api_client.py
brainrex/configuration.py
brainrex/rest.py
brainrex/api/__init__.py
brainrex/api/anomaly_api.py
brainrex/api/integrations_api.py
brainrex/api/language_api.py
brainrex/models/__init__.py
brainrex/models/candle_request.py
brainrex/models/candle_response.py
brainrex/models/error.py
brainrex/models/exchange.py
brainrex/models/exchange_assets_response.py
brainrex/models/exchange_assets_response_inner.py
brainrex/models/ohclv.py
brainrex/models/orderbook_request.py
brainrex/models/orderbook_response.py
brainrex/models/point_time_series.py
brainrex/models/supported_exchanges.py
brainrex/models/text.py
brainrex/models/ticker_response.py
brainrex/models/ticker_response_inner.py
brainrex/models/time_series.py
test/__init__.py
test/test_anomaly_api.py
test/test_candle_request.py
test/test_candle_response.py
test/test_error.py
test/test_exchange.py
test/test_exchange_assets_response.py
test/test_exchange_assets_response_inner.py
test/test_integrations_api.py
test/test_language_api.py
test/test_ohclv.py
test/test_orderbook_request.py
test/test_orderbook_response.py
test/test_point_time_series.py
test/test_supported_exchanges.py
test/test_text.py
test/test_ticker_response.py
test/test_ticker_response_inner.py
test/test_time_series.py
brainrex-1.0.3.dist-info/METADATA
brainrex-1.0.3.dist-info/WHEEL
brainrex-1.0.3.dist-info/top_level.txt
brainrex-1.0.3.dist-info/RECORD
