Metadata-Version: 2.1
Name: brainrex
Version: 1.0.3
Summary: Brainrex API
Home-page: https://github.com/brainrexAI/brainrex-python
Author-email: 
Keywords: Swagger,Brainrex API
Requires-Dist: urllib3 (>=1.15)
Requires-Dist: six (>=1.10)
Requires-Dist: certifi
Requires-Dist: python-dateutil
